django_celery_progress/__init__.py
django_celery_progress/admin.py
django_celery_progress/apps.py
django_celery_progress/models.py
django_celery_progress/progress.py
django_celery_progress/tasks.py
django_celery_progress/utils.py
django_celery_progress/views.py
django_celery_progress/migrations/0001_initial.py
django_celery_progress/migrations/__init__.py
django_celery_progress/templates/django_celery_progress/change_list.html
django_celery_progress-1.0.5.dist-info/LICENSE
django_celery_progress-1.0.5.dist-info/METADATA
django_celery_progress-1.0.5.dist-info/WHEEL
django_celery_progress-1.0.5.dist-info/top_level.txt
django_celery_progress-1.0.5.dist-info/RECORD
