Metadata-Version: 2.1
Name: django-celery-progress
Version: 1.0.5
Summary: A django app to monitor celery tasks with progress
Home-page: https://github.com/sandbox-pokhara/django-celery-progress
Author: Pradish Bijukchhe
Author-email: pradishbijukchhe@gmail.com
Project-URL: Bug Tracker, https://github.com/sandbox-pokhara/django-celery-progress/issues
Classifier: Programming Language :: Python :: 3
Classifier: License :: OSI Approved :: MIT License
Requires-Python: >=3
License-File: LICENSE
Requires-Dist: Django
Requires-Dist: celery
Requires-Dist: redis
